fibermorph/.gitignore
fibermorph/__init__.py
fibermorph/__main__.py
fibermorph/analysis/__init__.py
fibermorph/analysis/curvature_pipeline.py
fibermorph/analysis/parallel.py
fibermorph/analysis/section_pipeline.py
fibermorph/cli.py
fibermorph/core/__init__.py
fibermorph/core/curvature.py
fibermorph/core/filters.py
fibermorph/core/section.py
fibermorph/demo/__init__.py
fibermorph/demo/demo.py
fibermorph/demo/dummy_data.py
fibermorph/fibermorph.py
fibermorph/fibermorph_compat.py
fibermorph/gui/__init__.py
fibermorph/gui/app.py
fibermorph/gui/launcher.py
fibermorph/io/__init__.py
fibermorph/io/converters.py
fibermorph/io/readers.py
fibermorph/io/writers.py
fibermorph/processing/__init__.py
fibermorph/processing/binary.py
fibermorph/processing/geometry.py
fibermorph/processing/morphology.py
fibermorph/test/__init__.py
fibermorph/test/test_core_curvature.py
fibermorph/test/test_core_filters.py
fibermorph/test/test_core_section.py
fibermorph/test/test_io_readers.py
fibermorph/test/test_io_writers.py
fibermorph/test/test_processing_binary.py
fibermorph/test/test_processing_geometry.py
fibermorph/test/test_processing_morphology.py
fibermorph/test/test_utils_filesystem.py
fibermorph/test/test_utils_timing.py
fibermorph/test_data/SimArcData/Oct06_1855_32_017780_arc_data.csv
fibermorph/test_data/SimArcData/Oct06_1855_32_017780_arc_data.tiff
fibermorph/test_data/SimArcData/Oct06_1855_32_017780_arc_data_errordata.csv
fibermorph/utils/__init__.py
fibermorph/utils/filesystem.py
fibermorph/utils/logging_config.py
fibermorph/utils/timing.py
fibermorph/workflows.py
fibermorph-1.0.1.dist-info/LICENSE
fibermorph-1.0.1.dist-info/METADATA
fibermorph-1.0.1.dist-info/WHEEL
fibermorph-1.0.1.dist-info/entry_points.txt
fibermorph-1.0.1.dist-info/RECORD
