Metadata-Version: 2.1
Name: fibermorph
Version: 1.0.1
Summary: Interactive toolkit for analyzing hair fiber morphology with GUI and CLI
Home-page: https://github.com/lasisilab/fibermorph
License: LICENSE
Author: tinalasisi
Author-email: tina.lasisi@gmail.com
Requires-Python: >=3.10,<3.13
Classifier: License :: Other/Proprietary License
Classifier: Programming Language :: Python :: 3
Classifier: Programming Language :: Python :: 3.10
Classifier: Programming Language :: Python :: 3.11
Classifier: Programming Language :: Python :: 3.12
Provides-Extra: gui
Provides-Extra: raw
Provides-Extra: viz
Requires-Dist: joblib (>=1.3.2,<2.0.0)
Requires-Dist: matplotlib (>=3.8.2,<4.0.0) ; extra == "viz"
Requires-Dist: numpy (>=1.26.4,<2.0.0)
Requires-Dist: pandas (>=2.2.0,<3.0.0)
Requires-Dist: pillow (>=10.2.0,<11.0.0)
Requires-Dist: rawpy (>=0.19.0,<0.20.0) ; extra == "raw"
Requires-Dist: requests (>=2.31.0,<3.0.0)
Requires-Dist: scikit-image (>=0.22.0,<0.23.0)
Requires-Dist: scipy (>=1.8,<2.0)
Requires-Dist: streamlit (>=1.28.0,<2.0.0) ; extra == "gui"
Requires-Dist: tqdm (>=4.66.1,<5.0.0)
Project-URL: Repository, https://github.com/lasisilab/fibermorph
